{
  "agent_name": "NewsTrendsAnalyst",
  "ticker": "AMZN",
  "analysis_date": "2025-10-05",
  "signal": "bullish",
  "confidence": 0.6,
  "summary": "Recent news trends are broadly supportive, with more bullish than bearish evidence.",
  "bullish_factors": [
    "Recent company news flow is majority positive."
  ],
  "bearish_factors": [],
  "risk_flags": [
    "Litigious language appears in recent news"
  ],
  "key_metrics_used": {
    "article_count": 86,
    "raw_article_count": 86,
    "relevant_article_count": 11,
    "relevance_ratio": 0.12790697674418605,
    "positive_articles": 34,
    "negative_articles": 22,
    "avg_sentiment_score": 0.22093023255813954,
    "uncertainty_articles": 23,
    "litigious_articles": 5,
    "avg_uncertainty_hits": 0.37209302325581395,
    "has_trends_data": true,
    "current_week_avg": 49.0,
    "previous_week_avg": 46.0,
    "wow_change": 0.06521739130434782,
    "latest_search_interest": 49.0,
    "current_week_peak": 49.0,
    "news_score_diff": 1,
    "trend_score": 0,
    "combined_score": 0.4
  }
}