{
  "agent_name": "TechnicalAnalyst",
  "ticker": "AMZN",
  "analysis_date": "2025-11-30",
  "signal": "neutral",
  "confidence": 0.5,
  "summary": "The stock has both bullish and bearish factors, with a neutral signal due to the presence of risk flags and conflicting momentum indicators.",
  "bullish_factors": [
    "The 20-day moving average is above the 50-day moving average.",
    "The stock has positive 5-day return momentum.",
    "The stock has positive 20-day return momentum."
  ],
  "bearish_factors": [
    "Price is below the 20-day moving average.",
    "The 12-day EMA is below the 26-day EMA, suggesting weak momentum.",
    "MACD is below its signal line, indicating weakening momentum."
  ],
  "risk_flags": [
    "Low relative trading volume"
  ],
  "key_metrics_used": {
    "close": 233.22000122070312,
    "sma_20": 236.6715003967285,
    "sma_50": 227.56740051269531,
    "ema_12": 230.00846754671414,
    "ema_26": 230.81896209889305,
    "rsi_14": 39.64463937236477,
    "macd": -0.8104945521789091,
    "macd_signal": 0.23851858342917598,
    "return_5d": 0.07405361460925408,
    "return_20d": 0.04648658611674761,
    "volatility_20d": 0.030339107218556018,
    "volume_ratio_20d": 0.3797874180152676,
    "source_market_date": "2025-11-28"
  }
}