{
  "agent_name": "TechnicalAnalyst",
  "ticker": "LLY",
  "analysis_date": "2026-03-01",
  "signal": "bullish",
  "confidence": 0.7,
  "summary": "LLY is showing positive momentum with the price above its 20-day moving average and MACD above its signal line, but is also experiencing weak momentum with the 12-day EMA below the 26-day EMA.",
  "bullish_factors": [
    "Price is above the 20-day moving average.",
    "MACD is above its signal line, indicating positive momentum.",
    "The stock has positive 5-day return momentum.",
    "The stock has positive 20-day return momentum."
  ],
  "bearish_factors": [
    "The 20-day moving average is below the 50-day moving average.",
    "The 12-day EMA is below the 26-day EMA, suggesting weak momentum."
  ],
  "risk_flags": [],
  "key_metrics_used": {
    "close": 1051.989990234375,
    "sma_20": 1035.48056640625,
    "sma_50": 1051.6820385742187,
    "ema_12": 1035.4662518742841,
    "ema_26": 1038.350218904582,
    "rsi_14": 48.99721825884019,
    "macd": -2.883967030297981,
    "macd_signal": -4.38441967179143,
    "return_5d": 0.04206946854094595,
    "return_20d": 0.028907950075786948,
    "volatility_20d": 0.036237809147134765,
    "volume_ratio_20d": 1.1412689325485499,
    "source_market_date": "2026-02-27"
  }
}