{
  "agent_name": "FundamentalAnalyst",
  "ticker": "AMZN",
  "analysis_date": "2026-02-06",
  "signal": "bullish",
  "confidence": 0.8,
  "summary": "Amazon's strong gross margin, net margin, return on equity, and return on assets, combined with positive free cash flow and operating cash flow, outweigh the quick liquidity risk, supporting a bullish view.",
  "bullish_factors": [
    "Gross margin is strong.",
    "Net margin is healthy.",
    "Return on equity is strong.",
    "Return on assets is solid.",
    "Free cash flow is positive.",
    "Operating cash flow is positive."
  ],
  "bearish_factors": [],
  "risk_flags": [
    "Quick liquidity risk"
  ],
  "key_metrics_used": {
    "pe_ratio_ttm": null,
    "pe_ratio_forward": null,
    "revenue_growth_yoy": 0.02823618367412,
    "earnings_growth_yoy": null,
    "gross_margin": 0.458168689642952,
    "operating_margin": 0.124368742801453,
    "net_margin": 0.1235403561619562,
    "debt_to_equity": 0.3721722841886319,
    "current_ratio": 1.0508153482718283,
    "quick_ratio": 0.8750166280589895,
    "roe": 0.271373140500894,
    "roa": 0.1363646365345544,
    "free_cash_flow": 14937000000.0,
    "operating_cash_flow": 54459000000.0,
    "dividend_yield": null
  }
}