{
  "agent_name": "FundamentalAnalyst",
  "ticker": "XOM",
  "analysis_date": "2021-11-03",
  "signal": "bullish",
  "confidence": 0.7,
  "summary": "ExxonMobil (XOM) has a strong earnings profile with positive revenue growth and solid margins, but faces liquidity concerns.",
  "bullish_factors": [
    "Revenue growth is positive and above a modest growth threshold.",
    "Return on equity is strong.",
    "Return on assets is solid."
  ],
  "bearish_factors": [
    "Current ratio is below 1.0, suggesting weaker short-term liquidity."
  ],
  "risk_flags": [
    "Liquidity risk",
    "Quick liquidity risk"
  ],
  "key_metrics_used": {
    "pe_ratio_ttm": null,
    "pe_ratio_forward": null,
    "revenue_growth_yoy": 0.582652724270776,
    "earnings_growth_yoy": null,
    "gross_margin": null,
    "operating_margin": 0.1336170923051243,
    "net_margin": 0.0938908362543815,
    "debt_to_equity": null,
    "current_ratio": 0.8981343766166581,
    "quick_ratio": 0.8981343766166581,
    "roe": 0.1681310675077371,
    "roa": 0.0801929382692581,
    "free_cash_flow": null,
    "operating_cash_flow": null,
    "dividend_yield": null
  }
}