{
  "agent_name": "FundamentalAnalyst",
  "ticker": "XOM",
  "analysis_date": "2021-05-05",
  "signal": "bearish",
  "confidence": 0.8,
  "summary": "ExxonMobil (XOM) is bearish due to weaker short-term liquidity and liquidity risks, outweighing its neutral operating margins.",
  "bullish_factors": [],
  "bearish_factors": [
    "Current ratio is below 1.0, suggesting weaker short-term liquidity."
  ],
  "risk_flags": [
    "Liquidity risk",
    "Quick liquidity risk"
  ],
  "key_metrics_used": {
    "pe_ratio_ttm": null,
    "pe_ratio_forward": null,
    "revenue_growth_yoy": 0.0,
    "earnings_growth_yoy": null,
    "gross_margin": null,
    "operating_margin": 0.0651503609388036,
    "net_margin": 0.0495157253237566,
    "debt_to_equity": null,
    "current_ratio": 0.8012468827930175,
    "quick_ratio": 0.8012468827930175,
    "roe": 0.0695656605552512,
    "roa": 0.0327171405458848,
    "free_cash_flow": null,
    "operating_cash_flow": null,
    "dividend_yield": null
  }
}